kglab/__init__.py
kglab/decorators.py
kglab/esp.py
kglab/external_import.py
kglab/gpviz.py
kglab/kglab.py
kglab/pkg_types.py
kglab/srl.py
kglab/subg.py
kglab/topo.py
kglab/util.py
kglab/version.py
mkrefs/__init__.py
mkrefs/apidocs.py
mkrefs/biblio.py
mkrefs/cli.py
mkrefs/glossary.py
mkrefs/plugin.py
mkrefs/util.py
mkrefs/version.py
mkrefs-0.2.0.dist-info/LICENSE
mkrefs-0.2.0.dist-info/METADATA
mkrefs-0.2.0.dist-info/WHEEL
mkrefs-0.2.0.dist-info/entry_points.txt
mkrefs-0.2.0.dist-info/top_level.txt
mkrefs-0.2.0.dist-info/RECORD
