Metadata-Version: 2.1
Name: mkrefs
Version: 0.2.0
Summary: MkDocs plugin to generate semantic reference Markdown pages
Home-page: UNKNOWN
Author: Paco Nathan
Author-email: paco@derwen.ai
License: MIT
Keywords: apidocs,bibliography,documentation,glossary,kglab,knowledge graph,mkdocs,plugin,reference
Platform: UNKNOWN
Classifier: Development Status :: 4 - Beta
Classifier: Intended Audience :: Developers
Classifier: Intended Audience :: Information Technology
Classifier: Intended Audience :: Science/Research
Classifier: License :: OSI Approved :: MIT License
Classifier: Programming Language :: Python
Classifier: Programming Language :: Python :: 3 :: Only
Classifier: Topic :: Documentation
Classifier: Topic :: Software Development :: Documentation
Classifier: Topic :: Text Processing :: Markup :: Markdown
Requires-Python: >=3.6
Requires-Dist: Jinja2 (>=2.10.3)
Requires-Dist: PyYAML (>=5.1)
Requires-Dist: livereload (>=2.6.1)
Requires-Dist: mkdocs (>=1.0.4)
Requires-Dist: typer (>=0.3.2)
